Metadata-Version: 2.1
Name: clevertext
Version: 0.1
Summary: Keep and compare a history of changes to your Python strings.
Home-page: https://github.com/Pfython/clevertext
Author: Peter Fison
Author-email: peter@awsom.solutions
License: MIT License
Download-URL: https://github.com/Pfython/clevertext/archive/0.1.tar.gz
Keywords: clevertext,text,str,string,diff,NLP,AI,HTML,backup,restore,data,history,tracking,version,JSON,autosave,autodelete,to_lines,from_lines,to_list,from_list,database,utility,tool,clever
Platform: UNKNOWN
Classifier: Development Status :: 2 - Pre-Alpha
Classifier: Intended Audience :: Developers
Classifier: Operating System :: OS Independent
Classifier: Programming Language :: Python :: 3.10
Classifier: Programming Language :: Python :: 3.7
Classifier: Programming Language :: Python :: 3.8
Classifier: Programming Language :: Python :: 3.9
Classifier: Topic :: Software Development :: Libraries :: Python Modules
Classifier: Topic :: Software Development :: Object Brokering
Classifier: Topic :: System :: Logging
Classifier: Topic :: Utilities
Classifier: License :: OSI Approved :: MIT License
License-File: LICENSE
